anyhhope_hw_5_prj-0.1.0.data/data/configs/params.yaml
anyhhope_hw_5_prj-0.1.0.data/data/data/processed/.gitkeep
anyhhope_hw_5_prj-0.1.0.data/data/data/raw/.gitkeep
src/__init__.py
src/config_utils.py
src/dataset.py
src/modeling/__init__.py
src/modeling/inference.py
src/modeling/train.py
anyhhope_hw_5_prj-0.1.0.dist-info/LICENSE
anyhhope_hw_5_prj-0.1.0.dist-info/METADATA
anyhhope_hw_5_prj-0.1.0.dist-info/WHEEL
anyhhope_hw_5_prj-0.1.0.dist-info/top_level.txt
anyhhope_hw_5_prj-0.1.0.dist-info/RECORD
