Metadata-Version: 2.1
Name: anyhhope-hw-5-prj
Version: 0.1.0
Summary: MLops project
Author: anyhhope
License: MIT
License-File: LICENSE
